Metadata-Version: 1.1
Name: zwsp-steg-py
Version: 0.2.0
Summary: Zero-Width Space Steganography, encodes/decodes hidden messages as non printable/readable characters.
Home-page: https://github.com/enodari/zwsp-steg-py
Author: Edoardo Nodari
Author-email: info@nodari.me
License: Apache 2.0
Platform: UNKNOWN
Classifier: Development Status :: 3 - Alpha
Classifier: Intended Audience :: Developers
Classifier: License :: OSI Approved :: Apache Software License
Classifier: Natural Language :: English
Classifier: Programming Language :: Python :: 3.4
Classifier: Programming Language :: Python :: 3.6
